svc_toolkit/__init__.py
svc_toolkit/conversion/__init__.py
svc_toolkit/conversion/converter.py
svc_toolkit/conversion/converter_trainer.py
svc_toolkit/conversion/mixer.py
svc_toolkit/img/icon.png
svc_toolkit/img/loading.gif
svc_toolkit/main.py
svc_toolkit/models/manifest.yml
svc_toolkit/presenter/__init__.py
svc_toolkit/presenter/common.py
svc_toolkit/presenter/conversion.py
svc_toolkit/presenter/mixing.py
svc_toolkit/presenter/separation.py
svc_toolkit/presenter/training.py
svc_toolkit/separation/__init__.py
svc_toolkit/separation/audio.py
svc_toolkit/separation/constants.py
svc_toolkit/separation/data.py
svc_toolkit/separation/evaluator.py
svc_toolkit/separation/logger.py
svc_toolkit/separation/models.py
svc_toolkit/separation/preprocess.py
svc_toolkit/separation/separator.py
svc_toolkit/separation/utility.py
svc_toolkit/separation_evaluation.py
svc_toolkit/separation_preprocess.py
svc_toolkit/separation_train.py
svc_toolkit/utility/__init__.py
svc_toolkit/utility/functions.py
svc_toolkit/widget/__init__.py
svc_toolkit/widget/common.py
svc_toolkit/widget/conversion.py
svc_toolkit/widget/loading_overlay.py
svc_toolkit/widget/loading_window.py
svc_toolkit/widget/main_window.py
svc_toolkit/widget/mixing.py
svc_toolkit/widget/separation.py
svc_toolkit/widget/training.py
svc_toolkit-1.1.0.dist-info/LICENSE
svc_toolkit-1.1.0.dist-info/METADATA
svc_toolkit-1.1.0.dist-info/WHEEL
svc_toolkit-1.1.0.dist-info/entry_points.txt
svc_toolkit-1.1.0.dist-info/RECORD
