Metadata-Version: 2.1
Name: svc-toolkit
Version: 1.1.0
Summary: A self-contained singing voice conversion application using the so-vits-svc architecture, with Deep U-Net model for vocal separation feature and easy to use GUI.
Home-page: https://github.com/jljl1337/svc-toolkit
License: MIT
Author: jljl1337
Author-email: lckjack123@gmail.com
Requires-Python: >=3.10,<3.12
Classifier: License :: OSI Approved :: MIT License
Classifier: Operating System :: OS Independent
Classifier: Programming Language :: Python :: 3
Classifier: Programming Language :: Python :: 3.10
Classifier: Programming Language :: Python :: 3.11
Requires-Dist: huggingface-hub (==0.20.3)
Requires-Dist: librosa (==0.10.1)
Requires-Dist: lightning (==2.1.3)
Requires-Dist: matplotlib (==3.8.1)
Requires-Dist: numpy (==1.26.3)
Requires-Dist: pandas (==2.1.3)
Requires-Dist: pip (==24.0)
Requires-Dist: pyside6 (==6.6.1)
Requires-Dist: pyside6-utils (==1.2.2)
Requires-Dist: pyyaml (==6.0.1)
Requires-Dist: scikit-learn (==1.4.0)
Requires-Dist: scipy (==1.12.0)
Requires-Dist: so-vits-svc-fork (==4.1.40)
Requires-Dist: torch (==2.1.1)
Requires-Dist: torchaudio (==2.1.1)
Requires-Dist: torchmetrics (==1.2.0)
Project-URL: Documentation, https://jljl1337.github.io/svc-toolkit/
Project-URL: Repository, https://github.com/jljl1337/svc-toolkit
